graphql_relay/__init__.py
graphql_relay/py.typed
graphql_relay/version.py
graphql_relay/connection/__init__.py
graphql_relay/connection/array_connection.py
graphql_relay/connection/arrayconnection.py
graphql_relay/connection/connection.py
graphql_relay/mutation/__init__.py
graphql_relay/mutation/mutation.py
graphql_relay/node/__init__.py
graphql_relay/node/node.py
graphql_relay/node/plural.py
graphql_relay/utils/__init__.py
graphql_relay/utils/base64.py
graphql_relay-3.1.5.dist-info/LICENSE
graphql_relay-3.1.5.dist-info/METADATA
graphql_relay-3.1.5.dist-info/WHEEL
graphql_relay-3.1.5.dist-info/top_level.txt
graphql_relay-3.1.5.dist-info/RECORD
