Metadata-Version: 2.1
Name: graphql-relay
Version: 3.1.5
Summary: Relay library for graphql-core
Home-page: https://github.com/graphql-python/graphql-relay-py
Author: Syrus Akbary
Author-email: me@syrusakbary.com
License: MIT
Keywords: graphql relay api
Platform: UNKNOWN
Classifier: Development Status :: 5 - Production/Stable
Classifier: Intended Audience :: Developers
Classifier: Topic :: Software Development :: Libraries
Classifier: License :: OSI Approved :: MIT License
Classifier: Programming Language :: Python :: 3
Classifier: Programming Language :: Python :: 3.6
Classifier: Programming Language :: Python :: 3.7
Classifier: Programming Language :: Python :: 3.8
Classifier: Programming Language :: Python :: 3.9
Classifier: Programming Language :: Python :: 3.10
Classifier: Programming Language :: Python :: Implementation :: PyPy
Requires-Python: >=3.6,<4
License-File: LICENSE
